carthage/__init__.py
carthage/ansible.py
carthage/become_privileged.py
carthage/carthage_deployment.py
carthage/carthage_plugin.yml
carthage/cloud_init.py
carthage/console.py
carthage/container.py
carthage/debian.py
carthage/deployment.py
carthage/deployment_commands.py
carthage/dns.py
carthage/event.py
carthage/files.py
carthage/image.py
carthage/kvstore.py
carthage/local.py
carthage/machine.py
carthage/oci.py
carthage/pki.py
carthage/pki_utils.py
carthage/plugins.py
carthage/ports.py
carthage/pytest.py
carthage/pytest_plugin.py
carthage/runner_commands.py
carthage/setup_tasks.py
carthage/sh.py
carthage/skeleton.py
carthage/sonic.py
carthage/ssh.py
carthage/system_dependency.py
carthage/systemd.py
carthage/tb_utils.py
carthage/utils.py
carthage/vm.py
carthage/config/__init__.py
carthage/config/base.py
carthage/config/layout.py
carthage/config/schema.py
carthage/config/types.py
carthage/dependency_injection/__init__.py
carthage/dependency_injection/base.py
carthage/dependency_injection/introspection.py
carthage/entanglement/__init__.py
carthage/entanglement/instrumentation.py
carthage/entanglement/server.py
carthage/extra_packages/__init__.py
carthage/extra_packages/plugin.py
carthage/extra_packages/repo.py
carthage/extra_packages/resources/reprepro_distributions
carthage/modeling/__init__.py
carthage/modeling/ansible.py
carthage/modeling/base.py
carthage/modeling/decorators.py
carthage/modeling/example.py
carthage/modeling/implementation.py
carthage/modeling/utils.py
carthage/network/__init__.py
carthage/network/base.py
carthage/network/config.py
carthage/network/links.py
carthage/network/mac.py
carthage/network/namespace.py
carthage/network/switch.py
carthage/podman/__init__.py
carthage/podman/base.py
carthage/podman/carthage_plugin.yml
carthage/podman/container_host.py
carthage/podman/modeling.py
carthage/resources/80-net-setup-link.rules
carthage/resources/ansible-chroot-helper
carthage/resources/hadron-xorg-modes
carthage/resources/letsencrypt-production.pem
carthage-0.37.dist-info/licenses/LICENSE
carthage-0.37.dist-info/METADATA
carthage-0.37.dist-info/WHEEL
carthage-0.37.dist-info/top_level.txt
carthage-0.37.dist-info/RECORD
