Metadata-Version: 2.4
Name: carthage
Version: 0.37
Summary: A powerful Infrastructure as Code (IAC) framework
Author-email: Sam Hartman <sam.hartman@hadronindustries.com>
License: LGPL-3
Project-URL: Homepage, https://github.com/hadron/carthage
Project-URL: Documentation, https://carthage.readthedocs.io
Classifier: Intended Audience :: Developers
Classifier: License :: OSI Approved :: GNU Lesser General Public License v3 (LGPLv3)
Classifier: Programming Language :: Python :: 3.11
Requires-Python: >=3.11
License-File: LICENSE
Requires-Dist: lmdb
Requires-Dist: hvac
Requires-Dist: mako
Requires-Dist: python-dateutil
Requires-Dist: pyVmomi
Requires-Dist: pyyaml
Requires-Dist: netifaces
Requires-Dist: requests
Requires-Dist: setuptools
Requires-Dist: sh
Provides-Extra: dev
Requires-Dist: pytest; extra == "dev"
Requires-Dist: black; extra == "dev"
Dynamic: license-file
